lial_sms/__init__.py
lial_sms-1.0.3.dist-info/METADATA
lial_sms-1.0.3.dist-info/WHEEL
lial_sms-1.0.3.dist-info/top_level.txt
lial_sms-1.0.3.dist-info/RECORD
