Metadata-Version: 2.2
Name: lial_sms
Version: 1.0.3
Summary: Une librairie qui permet d\'intéragir avec le service de SMS de LIAL
Author: SIGIER Luc
Author-email: l.sigier@lialrioz.fr
Classifier: Programming Language :: Python :: 3
Classifier: Operating System :: OS Independent
Requires-Python: >=3.6
Requires-Dist: requests
Dynamic: author
Dynamic: author-email
Dynamic: classifier
Dynamic: requires-dist
Dynamic: requires-python
Dynamic: summary
